maraboupy/Marabou.py
maraboupy/MarabouNetwork.py
maraboupy/MarabouNetworkNNet.py
maraboupy/MarabouNetworkONNX.py
maraboupy/MarabouNetworkTF.py
maraboupy/MarabouUtils.py
maraboupy/__init__.py
maraboupy/test/__init__.py
maraboupy/test/test_core.py
maraboupy/test/test_dnc.py
maraboupy/test/test_equation.py
maraboupy/test/test_network.py
maraboupy/test/test_nnet.py
maraboupy/test/test_nnet_extensions.py
maraboupy/test/test_onnx.py
maraboupy/test/test_query.py
maraboupy/test/test_tf.py
test/__init__.py
test/test_core.py
test/test_dnc.py
test/test_equation.py
test/test_network.py
test/test_nnet.py
test/test_nnet_extensions.py
test/test_onnx.py
test/test_query.py
test/test_tf.py
maraboupy_NeuralNetworkVerification-0.0.0.dist-info/COPYING
maraboupy_NeuralNetworkVerification-0.0.0.dist-info/METADATA
maraboupy_NeuralNetworkVerification-0.0.0.dist-info/WHEEL
maraboupy_NeuralNetworkVerification-0.0.0.dist-info/top_level.txt
maraboupy_NeuralNetworkVerification-0.0.0.dist-info/RECORD
