Metadata-Version: 2.1
Name: maraboupy-NeuralNetworkVerification
Version: 0.0.0
Summary: Marabou Neural Network Verification Framework Python Interface
Home-page: https://github.com/NeuralNetworkVerification/Marabou
Author: Marabou
License: UNKNOWN
Keywords: neural network,formal verification
Platform: UNKNOWN
Classifier: License :: OSI Approved :: BSD License
Classifier: Programming Language :: Python :: 3
Classifier: Operating System :: MacOS
Classifier: Operating System :: POSIX :: Linux
Requires-Python: >=3.5
Requires-Dist: pybind11 (>=2.3.0)
